cryptoref.cpython-310-darwin.so
keybox/__init__.py
keybox/__main__.py
keybox/datasafe.py
keybox/editor.py
keybox/envelope.py
keybox/envelope_gpg.py
keybox/fileformat.py
keybox/keybox.py
keybox/main.py
keybox/pwgen.py
keybox/record.py
keybox/shell.py
keybox/stringutil.py
keybox/ui.py
keybox/backend/__init__.py
keybox/backend/argon2_cffi.py
keybox/backend/common.py
keybox/backend/cryptoref.py
keybox/backend/os_unix.py
keybox/backend/os_windows.py
keybox/backend/pynacl.py
keybox/backend/standard.py
keybox-0.5.0.dist-info/LICENSE
keybox-0.5.0.dist-info/METADATA
keybox-0.5.0.dist-info/WHEEL
keybox-0.5.0.dist-info/entry_points.txt
keybox-0.5.0.dist-info/top_level.txt
keybox-0.5.0.dist-info/RECORD
