Metadata-Version: 2.1
Name: keybox
Version: 0.5.0
Summary: Simple password manager. Stores secrets in encrypted tab-delimited table.
Home-page: https://github.com/rbrich/keybox
Author: Radek Brich
Author-email: radek.brich@devl.cz
License: MIT
Platform: UNKNOWN
License-File: LICENSE
Requires-Dist: pynacl
Requires-Dist: prompt-toolkit
Requires-Dist: blessed
Requires-Dist: pyperclip
